[
  {
    "kind": "TableSchema",
    "id": "",
    "isDeleted": false,
    "rev": "",
    "description": "",
    "name": "Crabs Data.csv",
    "createdBy": "",
    "acl": {
      "kind": "Acl",
      "owner": "",
      "aces": []
    },
    "createdDate": {
      "kind": "Date",
      "value": "2022-10-05T15:38:06.000Z"
    },
    "lastModifiedDate": {
      "kind": "Date",
      "value": "2022-10-21T10:00:10.000Z"
    },
    "urls": [],
    "tags": [],
    "meta": [],
    "url": {
      "kind": "Url",
      "uri": "https://github.com/tercen/test_dataset"
    },
    "version": "0.0.1",
    "authors": [],
    "isPublic": false,
    "projectId": "",
    "folderId": "",
    "nRows": 0,
    "columns": [],
    "dataDirectory": "",
    "relation": {
      "kind": "Relation",
      "id": "e23790fc-67bf-4db1-ad84-a2eb51d5d5b2"
    }
  }
]